setup.py
aocframework/__init__.py
aocframework/framework.py
aocframework.egg-info/PKG-INFO
aocframework.egg-info/SOURCES.txt
aocframework.egg-info/dependency_links.txt
aocframework.egg-info/not-zip-safe
aocframework.egg-info/requires.txt
aocframework.egg-info/top_level.txt