Metadata-Version: 1.0
Name: aocframework
Version: 0.2
Summary: Framework for solving tasks at adventofcode.com
Home-page: https://github.com/roboxv/aocframework
Author: robox
Author-email: root@roboxv.pro
License: WTFPL
Platform: UNKNOWN
